mirror/__init__.py
mirror/__main__.py
mirror/update.py
mirror/command/__init__.py
mirror/command/crontab.py
mirror/command/daemon.py
mirror/config/__init__.py
mirror/event/__init__.py
mirror/logger/__init__.py
mirror/plugin/__init__.py
mirror/socket/__init__.py
mirror/structure/__init__.py
mirror/sync/__init__.py
mirror/sync/bandersnatch.py
mirror/sync/ftpsync.py
mirror/sync/lftp.py
mirror/sync/local.py
mirror/sync/rsync.py
mirror/toolbox/__init__.py
mirror.py-1.0.0rc3.dist-info/LICENSE
mirror.py-1.0.0rc3.dist-info/METADATA
mirror.py-1.0.0rc3.dist-info/WHEEL
mirror.py-1.0.0rc3.dist-info/entry_points.txt
mirror.py-1.0.0rc3.dist-info/top_level.txt
mirror.py-1.0.0rc3.dist-info/RECORD
